diopter/__init__.py
diopter/bisector.py
diopter/compiler.py
diopter/generator.py
diopter/py.typed
diopter/reducer.py
diopter/repository.py
diopter/sanitizer.py
diopter/utils.py
diopter-0.0.31.dist-info/licenses/LICENSE
tests/__init__.py
tests/bisect_test.py
tests/compilation_command_parsing_test.py
tests/compiler_serialization_test.py
tests/compiler_test.py
tests/preprocessor_test.py
tests/reducer_test.py
tests/sanitizer_test.py
diopter-0.0.31.dist-info/METADATA
diopter-0.0.31.dist-info/WHEEL
diopter-0.0.31.dist-info/top_level.txt
diopter-0.0.31.dist-info/RECORD
