Metadata-Version: 2.4
Name: diopter
Version: 0.0.31
Summary: A library for building differential tests
Home-page: https://github.com/DeadCodeProductions/diopter
Author: Theodoros Theodoridis, Yann Girsberger
Author-email: theodort@inf.ethz.ch
License: Apache License 2.0
Classifier: Programming Language :: Python :: 3
Requires-Python: >=3.10
License-File: LICENSE
Dynamic: license-file
